aiobotocore/__init__.py
aiobotocore/_endpoint_helpers.py
aiobotocore/args.py
aiobotocore/client.py
aiobotocore/config.py
aiobotocore/credentials.py
aiobotocore/endpoint.py
aiobotocore/eventstream.py
aiobotocore/handlers.py
aiobotocore/hooks.py
aiobotocore/paginate.py
aiobotocore/parsers.py
aiobotocore/response.py
aiobotocore/session.py
aiobotocore/signers.py
aiobotocore/utils.py
aiobotocore/waiter.py
aio_botocore-1.3.3.dist-info/LICENSE
aio_botocore-1.3.3.dist-info/WHEEL
aio_botocore-1.3.3.dist-info/METADATA
aio_botocore-1.3.3.dist-info/RECORD
